truncated_triangle_distribution_mean/__init__.py
truncated_triangle_distribution_mean/py.typed
truncated_triangle_distribution_mean/truncated_triangle_distribution_mean.py
truncated_triangle_distribution_mean-0.1.2.dist-info/METADATA
truncated_triangle_distribution_mean-0.1.2.dist-info/WHEEL
truncated_triangle_distribution_mean-0.1.2.dist-info/licenses/LICENSE
truncated_triangle_distribution_mean-0.1.2.dist-info/RECORD
