Metadata-Version: 2.3
Name: truncated_triangle_distribution_mean
Version: 0.1.2
Summary: A small package that calculates the mean of a truncated triangular distribution analytically.
Project-URL: repository, https://github.com/JohnScolaro/truncated_triangle_distribution_mean
Author-email: John Scolaro <johnscolaro95@gmail.com>
License: Copyright (c) 2024 John Scolaro
License-File: LICENSE
Keywords: distribution,triangular,truncated
Classifier: License :: OSI Approved :: MIT License
Classifier: Operating System :: OS Independent
Classifier: Programming Language :: Python :: 3
Classifier: Topic :: Scientific/Engineering :: Mathematics
Requires-Python: >=3.10
Provides-Extra: dev
Requires-Dist: mypy==1.11.2; extra == 'dev'
Requires-Dist: pre-commit==3.8.0; extra == 'dev'
Requires-Dist: pytest==8.3.2; extra == 'dev'
Requires-Dist: ruff==0.6.2; extra == 'dev'
Requires-Dist: scipy==1.14.1; extra == 'dev'
